MANIFEST.in
README.md
setup.py
sqlalchemy_models/__init__.py
sqlalchemy_models/broker.py
sqlalchemy_models/definitions.json
sqlalchemy_models/exchange.py
sqlalchemy_models/todo.py
sqlalchemy_models/user.py
sqlalchemy_models/util.py
sqlalchemy_models/wallet.py
sqlalchemy_models.egg-info/PKG-INFO
sqlalchemy_models.egg-info/SOURCES.txt
sqlalchemy_models.egg-info/dependency_links.txt
sqlalchemy_models.egg-info/requires.txt
sqlalchemy_models.egg-info/top_level.txt
test/test_lifecycle.py