Metadata-Version: 1.1
Name: sqlalchemy-models
Version: 0.0.6
Summary:  Generic data models for an application using SQLAlchemy.
Home-page: https://github.com/TAPPGuild/sqlalchemy-models
Author: Git Guild
Author-email: support@gitguild.com
License: MIT
Platform: UNKNOWN
Classifier: License :: OSI Approved :: MIT License
Classifier: Programming Language :: Python :: 2
Classifier: Topic :: Software Development :: Libraries
